jarvisui1/Jarvis_UI.py
jarvisui1/__init__.py
jarvisui1-0.0.5.dist-info/LICENSE
jarvisui1-0.0.5.dist-info/METADATA
jarvisui1-0.0.5.dist-info/WHEEL
jarvisui1-0.0.5.dist-info/top_level.txt
jarvisui1-0.0.5.dist-info/RECORD
