Metadata-Version: 2.1
Name: jarvisui1
Version: 0.0.5
Summary: ui for jarvis ui
Home-page: UNKNOWN
Author: Aditya
Author-email: adityagarg1165@gmail.com
License: UNKNOWN
Keywords: arithmetic,math,mathematics,python tutorial,jarvis
Platform: UNKNOWN
Classifier: Development Status :: 1 - Planning
Classifier: Intended Audience :: Developers
Classifier: Programming Language :: Python :: 3
Classifier: Operating System :: Unix
Classifier: Operating System :: MacOS :: MacOS X
Classifier: Operating System :: Microsoft :: Windows
License-File: LICENSE
